CHANGES.txt
DEPENDENCES.txt
README.txt
setup.py
src/pd/__init__.py
src/pd.refchecker.egg-info/PKG-INFO
src/pd.refchecker.egg-info/SOURCES.txt
src/pd.refchecker.egg-info/dependency_links.txt
src/pd.refchecker.egg-info/entry_points.txt
src/pd.refchecker.egg-info/namespace_packages.txt
src/pd.refchecker.egg-info/not-zip-safe
src/pd.refchecker.egg-info/requires.txt
src/pd.refchecker.egg-info/top_level.txt
src/pd/refchecker/__init__.py
src/pd/refchecker/configure.zcml
src/pd/refchecker/interfaces.py
src/pd/refchecker/pd.refchecker.txt
src/pd/refchecker/pdrefchecker.py
src/pd/refchecker/refchecker.py
src/pd/refchecker/browser/__init__.py
src/pd/refchecker/browser/configure.zcml
src/pd/refchecker/browser/xmlrpcgetreference.py
src/pd/refchecker/etc/pd.refchecker-configure.zcml
