Metadata-Version: 1.0
Name: pd.refchecker
Version: 0.0.1
Summary: Product intendent to check validity of external reference on site
Home-page: http://www.dreambot.ru/pd.refchecker/DreamBotOtherReleases/pd.refchecker
Author: Andrey Orlov
Author-email: dbdt@dreambot.ru
License: GPL v2.1
Platform: UNKNOWN
Classifier: Intended Audience :: Developers
Classifier: License :: OSI Approved :: GNU General Public License (GPL)
Classifier: Programming Language :: Python
Classifier: Operating System :: OS Independent
